[
  {
    "name": "11-0002 TPG",
    "rgb": {
      "r": 233,
      "g": 225,
      "b": 218
    },
    "hex": "#E9E1DA",
    "lab": {
      "l": 89.96,
      "a": 2.01,
      "b": 4.21
    }
  },
  {
    "name": "11-1400 TPG",
    "rgb": {
      "r": 238,
      "g": 219,
      "b": 223
    },
    "hex": "#EEDBDF",
    "lab": {
      "l": 89.14,
      "a": 7.47,
      "b": 0.7
    }
  },
  {
    "name": "11-3900 TPG",
    "rgb": {
      "r": 239,
      "g": 239,
      "b": 237
    },
    "hex": "#EFEFED",
    "lab": {
      "l": 94.24,
      "a": -0.04,
      "b": 0.66
    }
  },
  {
    "name": "11-4101 TPG",
    "rgb": {
      "r": 241,
      "g": 241,
      "b": 238
    },
    "hex": "#F1F1EE",
    "lab": {
      "l": 94.9,
      "a": -0.3,
      "b": 1.18
    }
  },
  {
    "name": "12-0003 TPG",
    "rgb": {
      "r": 230,
      "g": 224,
      "b": 217
    },
    "hex": "#E6E0D9",
    "lab": {
      "l": 89.44,
      "a": 1.72,
      "b": 3.82
    }
  },
  {
    "name": "12-0107 TPG",
    "rgb": {
      "r": 189,
      "g": 222,
      "b": 195
    },
    "hex": "#BDDEC3",
    "lab": {
      "l": 85.14,
      "a": -14.78,
      "b": 8.53
    }
  },
  {
    "name": "12-0230 TPG",
    "rgb": {
      "r": 195,
      "g": 229,
      "b": 186
    },
    "hex": "#C3E5BA",
    "lab": {
      "l": 87.39,
      "a": -17.42,
      "b": 16.5
    }
  },
  {
    "name": "12-0430 TPG",
    "rgb": {
      "r": 221,
      "g": 240,
      "b": 150
    },
    "hex": "#DDF096",
    "lab": {
      "l": 91.67,
      "a": -16.32,
      "b": 40.56
    }
  },
  {
    "name": "12-0508 TPG",
    "rgb": {
      "r": 232,
      "g": 231,
      "b": 223
    },
    "hex": "#E8E7DF",
    "lab": {
      "l": 91.34,
      "a": -0.13,
      "b": 3.83
    }
  },
  {
    "name": "12-0540 TPG",
    "rgb": {
      "r": 221,
      "g": 232,
      "b": 173
    },
    "hex": "#DDE8AD",
    "lab": {
      "l": 89.8,
      "a": -10,
      "b": 26.63
    }
  },
  {
    "name": "12-0549 TPG",
    "rgb": {
      "r": 214,
      "g": 238,
      "b": 122
    },
    "hex": "#D6EE7A",
    "lab": {
      "l": 90.27,
      "a": -20.27,
      "b": 51.69
    }
  },
  {
    "name": "12-0550 TPG",
    "rgb": {
      "r": 226,
      "g": 240,
      "b": 130
    },
    "hex": "#E2F082",
    "lab": {
      "l": 91.67,
      "a": -15.53,
      "b": 50.13
    }
  },
  {
    "name": "12-0618 TPG",
    "rgb": {
      "r": 227,
      "g": 220,
      "b": 168
    },
    "hex": "#E3DCA8",
    "lab": {
      "l": 87.28,
      "a": -3.08,
      "b": 26.54
    }
  },
  {
    "name": "12-0640 TPG",
    "rgb": {
      "r": 245,
      "g": 230,
      "b": 134
    },
    "hex": "#F5E686",
    "lab": {
      "l": 90.9,
      "a": -3.13,
      "b": 47.91
    }
  },
  {
    "name": "12-0641 TPG",
    "rgb": {
      "r": 225,
      "g": 236,
      "b": 123
    },
    "hex": "#E1EC7B",
    "lab": {
      "l": 90.54,
      "a": -14.59,
      "b": 51.81
    }
  },
  {
    "name": "12-0650 TPG",
    "rgb": {
      "r": 240,
      "g": 227,
      "b": 50
    },
    "hex": "#F0E332",
    "lab": {
      "l": 89.14,
      "a": -7.85,
      "b": 78.43
    }
  },
  {
    "name": "12-0705 TPG",
    "rgb": {
      "r": 230,
      "g": 221,
      "b": 209
    },
    "hex": "#E6DDD1",
    "lab": {
      "l": 88.55,
      "a": 1.85,
      "b": 6.93
    }
  },
  {
    "name": "12-0719 TPG",
    "rgb": {
      "r": 245,
      "g": 239,
      "b": 114
    },
    "hex": "#F5EF72",
    "lab": {
      "l": 93.02,
      "a": -8.7,
      "b": 59.11
    }
  },
  {
    "name": "12-0723 TPG",
    "rgb": {
      "r": 229,
      "g": 221,
      "b": 138
    },
    "hex": "#E5DD8A",
    "lab": {
      "l": 87.19,
      "a": -5.17,
      "b": 41.35
    }
  },
  {
    "name": "12-0730 TPG",
    "rgb": {
      "r": 248,
      "g": 226,
      "b": 161
    },
    "hex": "#F8E2A1",
    "lab": {
      "l": 90.58,
      "a": 1.49,
      "b": 34.51
    }
  },
  {
    "name": "12-0743 TPG",
    "rgb": {
      "r": 243,
      "g": 242,
      "b": 145
    },
    "hex": "#F3F291",
    "lab": {
      "l": 93.85,
      "a": -8.91,
      "b": 45.94
    }
  },
  {
    "name": "12-0745 TPG",
    "rgb": {
      "r": 228,
      "g": 238,
      "b": 164
    },
    "hex": "#E4EEA4",
    "lab": {
      "l": 91.89,
      "a": -10.85,
      "b": 34.09
    }
  },
  {
    "name": "12-1015 TPG",
    "rgb": {
      "r": 241,
      "g": 204,
      "b": 188
    },
    "hex": "#F1CCBC",
    "lab": {
      "l": 84.92,
      "a": 12.69,
      "b": 13.4
    }
  },
  {
    "name": "12-1121 TPG",
    "rgb": {
      "r": 253,
      "g": 208,
      "b": 185
    },
    "hex": "#FDD0B9",
    "lab": {
      "l": 87.18,
      "a": 13.96,
      "b": 18.05
    }
  },
  {
    "name": "12-1306 TPG",
    "rgb": {
      "r": 232,
      "g": 221,
      "b": 208
    },
    "hex": "#E8DDD0",
    "lab": {
      "l": 88.58,
      "a": 2.94,
      "b": 7.46
    }
  },
  {
    "name": "12-1505 TPG",
    "rgb": {
      "r": 237,
      "g": 215,
      "b": 211
    },
    "hex": "#EDD7D3",
    "lab": {
      "l": 87.73,
      "a": 7.9,
      "b": 5.05
    }
  },
  {
    "name": "12-2400 TPG",
    "rgb": {
      "r": 233,
      "g": 216,
      "b": 213
    },
    "hex": "#E9D8D5",
    "lab": {
      "l": 87.74,
      "a": 5.93,
      "b": 3.88
    }
  },
  {
    "name": "12-2900 TPG",
    "rgb": {
      "r": 230,
      "g": 206,
      "b": 217
    },
    "hex": "#E6CED9",
    "lab": {
      "l": 84.96,
      "a": 10.52,
      "b": -2.02
    }
  },
  {
    "name": "12-4001 TPG",
    "rgb": {
      "r": 222,
      "g": 217,
      "b": 211
    },
    "hex": "#DED9D3",
    "lab": {
      "l": 86.97,
      "a": 1.42,
      "b": 3.7
    }
  },
  {
    "name": "12-5211 TPG",
    "rgb": {
      "r": 192,
      "g": 216,
      "b": 222
    },
    "hex": "#C0D8DE",
    "lab": {
      "l": 84.56,
      "a": -7.14,
      "b": -6.48
    }
  },
  {
    "name": "12-5806 TPG",
    "rgb": {
      "r": 198,
      "g": 230,
      "b": 212
    },
    "hex": "#C6E6D4",
    "lab": {
      "l": 88.33,
      "a": -14.1,
      "b": 4.68
    }
  },
  {
    "name": "12-6000 TPG",
    "rgb": {
      "r": 202,
      "g": 231,
      "b": 205
    },
    "hex": "#CAE7CD",
    "lab": {
      "l": 88.86,
      "a": -14.17,
      "b": 9.24
    }
  },
  {
    "name": "13-0005 TPG",
    "rgb": {
      "r": 202,
      "g": 195,
      "b": 194
    },
    "hex": "#CAC3C2",
    "lab": {
      "l": 79.3,
      "a": 2.7,
      "b": 1.53
    }
  },
  {
    "name": "13-0216 TPG",
    "rgb": {
      "r": 179,
      "g": 225,
      "b": 160
    },
    "hex": "#B3E1A0",
    "lab": {
      "l": 84.62,
      "a": -23.68,
      "b": 25.52
    }
  },
  {
    "name": "13-1218 TPG",
    "rgb": {
      "r": 255,
      "g": 205,
      "b": 186
    },
    "hex": "#FFCDBA",
    "lab": {
      "l": 86.7,
      "a": 16.86,
      "b": 17.07
    }
  },
  {
    "name": "13-1307 TPG",
    "rgb": {
      "r": 249,
      "g": 184,
      "b": 164
    },
    "hex": "#F9B8A4",
    "lab": {
      "l": 80.81,
      "a": 23.69,
      "b": 20.48
    }
  },
  {
    "name": "13-1330 TPG",
    "rgb": {
      "r": 255,
      "g": 193,
      "b": 172
    },
    "hex": "#FFC1AC",
    "lab": {
      "l": 84.14,
      "a": 23.17,
      "b": 21.43
    }
  },
  {
    "name": "13-1418 TPG",
    "rgb": {
      "r": 240,
      "g": 187,
      "b": 172
    },
    "hex": "#F0BBAC",
    "lab": {
      "l": 80.63,
      "a": 18.33,
      "b": 16.19
    }
  },
  {
    "name": "13-2009 TPG",
    "rgb": {
      "r": 238,
      "g": 188,
      "b": 190
    },
    "hex": "#EEBCBE",
    "lab": {
      "l": 80.94,
      "a": 20.28,
      "b": 6.42
    }
  },
  {
    "name": "13-2016 TPG",
    "rgb": {
      "r": 250,
      "g": 181,
      "b": 195
    },
    "hex": "#FAB5C3",
    "lab": {
      "l": 80.72,
      "a": 27.88,
      "b": 4.07
    }
  },
  {
    "name": "13-2705 TPG",
    "rgb": {
      "r": 249,
      "g": 206,
      "b": 222
    },
    "hex": "#F9CEDE",
    "lab": {
      "l": 86.99,
      "a": 17.44,
      "b": -1.39
    }
  },
  {
    "name": "13-2930 TPG",
    "rgb": {
      "r": 220,
      "g": 198,
      "b": 209
    },
    "hex": "#DCC6D1",
    "lab": {
      "l": 81.95,
      "a": 10.4,
      "b": -2.68
    }
  },
  {
    "name": "13-3905 TPG",
    "rgb": {
      "r": 199,
      "g": 195,
      "b": 206
    },
    "hex": "#C7C3CE",
    "lab": {
      "l": 79.35,
      "a": 3.4,
      "b": -5.25
    }
  },
  {
    "name": "13-4005 TPG",
    "rgb": {
      "r": 196,
      "g": 190,
      "b": 201
    },
    "hex": "#C4BEC9",
    "lab": {
      "l": 77.5,
      "a": 3.94,
      "b": -4.67
    }
  },
  {
    "name": "13-4016 TPG",
    "rgb": {
      "r": 191,
      "g": 208,
      "b": 230
    },
    "hex": "#BFD0E6",
    "lab": {
      "l": 82.59,
      "a": -2.58,
      "b": -13.17
    }
  },
  {
    "name": "13-4520 TPG",
    "rgb": {
      "r": 160,
      "g": 214,
      "b": 237
    },
    "hex": "#A0D6ED",
    "lab": {
      "l": 82.17,
      "a": -14.58,
      "b": -17.66
    }
  },
  {
    "name": "13-5320 TPG",
    "rgb": {
      "r": 160,
      "g": 222,
      "b": 212
    },
    "hex": "#A0DED4",
    "lab": {
      "l": 83.49,
      "a": -22.23,
      "b": -2.99
    }
  },
  {
    "name": "13-5512 TPG",
    "rgb": {
      "r": 171,
      "g": 220,
      "b": 211
    },
    "hex": "#ABDCD3",
    "lab": {
      "l": 83.64,
      "a": -18.09,
      "b": -1.89
    }
  },
  {
    "name": "13-5612 TPG",
    "rgb": {
      "r": 164,
      "g": 226,
      "b": 212
    },
    "hex": "#A4E2D4",
    "lab": {
      "l": 84.96,
      "a": -23.14,
      "b": -0.67
    }
  },
  {
    "name": "13-5615 TPG",
    "rgb": {
      "r": 158,
      "g": 224,
      "b": 198
    },
    "hex": "#9EE0C6",
    "lab": {
      "l": 83.87,
      "a": -26.2,
      "b": 5.03
    }
  },
  {
    "name": "13-5710 TPG",
    "rgb": {
      "r": 148,
      "g": 220,
      "b": 190
    },
    "hex": "#94DCBE",
    "lab": {
      "l": 81.79,
      "a": -28.65,
      "b": 6.15
    }
  },
  {
    "name": "13-6010 TPG",
    "rgb": {
      "r": 168,
      "g": 222,
      "b": 201
    },
    "hex": "#A8DEC9",
    "lab": {
      "l": 83.98,
      "a": -21.39,
      "b": 3.48
    }
  },
  {
    "name": "13-6226 TPG",
    "rgb": {
      "r": 178,
      "g": 222,
      "b": 175
    },
    "hex": "#B2DEAF",
    "lab": {
      "l": 84.07,
      "a": -21.22,
      "b": 17.19
    }
  },
  {
    "name": "14-0120 TPG",
    "rgb": {
      "r": 142,
      "g": 200,
      "b": 152
    },
    "hex": "#8EC898",
    "lab": {
      "l": 75.28,
      "a": -26.62,
      "b": 16.9
    }
  },
  {
    "name": "14-0207 TPG",
    "rgb": {
      "r": 180,
      "g": 176,
      "b": 171
    },
    "hex": "#B4B0AB",
    "lab": {
      "l": 72.01,
      "a": 1.3,
      "b": 3.1
    }
  },
  {
    "name": "14-0225 TPG",
    "rgb": {
      "r": 156,
      "g": 209,
      "b": 153
    },
    "hex": "#9CD199",
    "lab": {
      "l": 78.62,
      "a": -25.28,
      "b": 20.67
    }
  },
  {
    "name": "14-0440 TPG",
    "rgb": {
      "r": 199,
      "g": 205,
      "b": 91
    },
    "hex": "#C7CD5B",
    "lab": {
      "l": 80.01,
      "a": -11.86,
      "b": 53.62
    }
  },
  {
    "name": "14-0702 TPG",
    "rgb": {
      "r": 183,
      "g": 174,
      "b": 170
    },
    "hex": "#B7AEAA",
    "lab": {
      "l": 71.55,
      "a": 3.12,
      "b": 3.18
    }
  },
  {
    "name": "14-1242 TPG",
    "rgb": {
      "r": 255,
      "g": 173,
      "b": 132
    },
    "hex": "#FFAD84",
    "lab": {
      "l": 79.49,
      "a": 31.17,
      "b": 36.18
    }
  },
  {
    "name": "14-1320 TPG",
    "rgb": {
      "r": 248,
      "g": 170,
      "b": 155
    },
    "hex": "#F8AA9B",
    "lab": {
      "l": 77.36,
      "a": 29.35,
      "b": 20.62
    }
  },
  {
    "name": "14-1417 TPG",
    "rgb": {
      "r": 236,
      "g": 162,
      "b": 142
    },
    "hex": "#ECA28E",
    "lab": {
      "l": 73.98,
      "a": 27.8,
      "b": 22.65
    }
  },
  {
    "name": "14-1430 TPG",
    "rgb": {
      "r": 243,
      "g": 170,
      "b": 153
    },
    "hex": "#F3AA99",
    "lab": {
      "l": 76.72,
      "a": 27.21,
      "b": 21.02
    }
  },
  {
    "name": "14-1431 TPG",
    "rgb": {
      "r": 255,
      "g": 170,
      "b": 140
    },
    "hex": "#FFAA8C",
    "lab": {
      "l": 78.77,
      "a": 31.78,
      "b": 31.12
    }
  },
  {
    "name": "14-1440 TPG",
    "rgb": {
      "r": 255,
      "g": 177,
      "b": 148
    },
    "hex": "#FFB194",
    "lab": {
      "l": 80.59,
      "a": 30,
      "b": 29.52
    }
  },
  {
    "name": "14-1602 TPG",
    "rgb": {
      "r": 229,
      "g": 158,
      "b": 145
    },
    "hex": "#E59E91",
    "lab": {
      "l": 72.18,
      "a": 27.11,
      "b": 18.92
    }
  },
  {
    "name": "14-1715 TPG",
    "rgb": {
      "r": 234,
      "g": 166,
      "b": 175
    },
    "hex": "#EAA6AF",
    "lab": {
      "l": 75.1,
      "a": 28.27,
      "b": 6.24
    }
  },
  {
    "name": "14-1816 TPG",
    "rgb": {
      "r": 237,
      "g": 161,
      "b": 176
    },
    "hex": "#EDA1B0",
    "lab": {
      "l": 74.33,
      "a": 31.91,
      "b": 5.32
    }
  },
  {
    "name": "14-2216 TPG",
    "rgb": {
      "r": 248,
      "g": 155,
      "b": 183
    },
    "hex": "#F89BB7",
    "lab": {
      "l": 74.64,
      "a": 39.1,
      "b": 2.21
    }
  },
  {
    "name": "14-2609 TPG",
    "rgb": {
      "r": 227,
      "g": 172,
      "b": 202
    },
    "hex": "#E3ACCA",
    "lab": {
      "l": 76.32,
      "a": 25.24,
      "b": -6.48
    }
  },
  {
    "name": "14-3512 TPG",
    "rgb": {
      "r": 208,
      "g": 183,
      "b": 218
    },
    "hex": "#D0B7DA",
    "lab": {
      "l": 77.44,
      "a": 14.09,
      "b": -13.8
    }
  },
  {
    "name": "14-3610 TPG",
    "rgb": {
      "r": 205,
      "g": 182,
      "b": 210
    },
    "hex": "#CDB6D2",
    "lab": {
      "l": 76.56,
      "a": 12.65,
      "b": -10.96
    }
  },
  {
    "name": "14-3700 TPG",
    "rgb": {
      "r": 188,
      "g": 178,
      "b": 178
    },
    "hex": "#BCB2B2",
    "lab": {
      "l": 73.35,
      "a": 3.99,
      "b": 1.39
    }
  },
  {
    "name": "14-3715 TPG",
    "rgb": {
      "r": 196,
      "g": 177,
      "b": 207
    },
    "hex": "#C4B1CF",
    "lab": {
      "l": 74.57,
      "a": 11.01,
      "b": -12.26
    }
  },
  {
    "name": "14-3802 TPG",
    "rgb": {
      "r": 187,
      "g": 180,
      "b": 180
    },
    "hex": "#BBB4B4",
    "lab": {
      "l": 73.73,
      "a": 2.81,
      "b": 0.97
    }
  },
  {
    "name": "14-3813 TPG",
    "rgb": {
      "r": 177,
      "g": 175,
      "b": 200
    },
    "hex": "#B1AFC8",
    "lab": {
      "l": 72.11,
      "a": 4.43,
      "b": -12.62
    }
  },
  {
    "name": "14-3915 TPG",
    "rgb": {
      "r": 180,
      "g": 178,
      "b": 203
    },
    "hex": "#B4B2CB",
    "lab": {
      "l": 73.28,
      "a": 4.47,
      "b": -12.08
    }
  },
  {
    "name": "14-3926 TPG",
    "rgb": {
      "r": 181,
      "g": 180,
      "b": 213
    },
    "hex": "#B5B4D5",
    "lab": {
      "l": 73.92,
      "a": 5.16,
      "b": -16.65
    }
  },
  {
    "name": "14-3935 TPG",
    "rgb": {
      "r": 176,
      "g": 177,
      "b": 214
    },
    "hex": "#B0B1D6",
    "lab": {
      "l": 72.86,
      "a": 4.91,
      "b": -18.78
    }
  },
  {
    "name": "14-4015 TPG",
    "rgb": {
      "r": 174,
      "g": 197,
      "b": 224
    },
    "hex": "#AEC5E0",
    "lab": {
      "l": 78.1,
      "a": -3.81,
      "b": -16.73
    }
  },
  {
    "name": "14-4109 TPG",
    "rgb": {
      "r": 189,
      "g": 184,
      "b": 187
    },
    "hex": "#BDB8BB",
    "lab": {
      "l": 75.07,
      "a": 2.85,
      "b": -0.84
    }
  },
  {
    "name": "14-4111 TPG",
    "rgb": {
      "r": 179,
      "g": 193,
      "b": 212
    },
    "hex": "#B3C1D4",
    "lab": {
      "l": 77.2,
      "a": -1.94,
      "b": -11.36
    }
  },
  {
    "name": "14-4116 TPG",
    "rgb": {
      "r": 175,
      "g": 170,
      "b": 171
    },
    "hex": "#AFAAAB",
    "lab": {
      "l": 69.97,
      "a": 2.3,
      "b": 0.25
    }
  },
  {
    "name": "14-4130 TPG",
    "rgb": {
      "r": 167,
      "g": 197,
      "b": 230
    },
    "hex": "#A7C5E6",
    "lab": {
      "l": 77.88,
      "a": -5.24,
      "b": -20.4
    }
  },
  {
    "name": "14-4205 TPG",
    "rgb": {
      "r": 158,
      "g": 162,
      "b": 167
    },
    "hex": "#9EA2A7",
    "lab": {
      "l": 66.25,
      "a": -0.3,
      "b": -3.21
    }
  },
  {
    "name": "14-4216 TPG",
    "rgb": {
      "r": 182,
      "g": 184,
      "b": 184
    },
    "hex": "#B6B8B8",
    "lab": {
      "l": 74.47,
      "a": -0.55,
      "b": -0.61
    }
  },
  {
    "name": "14-4309 TPG",
    "rgb": {
      "r": 183,
      "g": 188,
      "b": 194
    },
    "hex": "#B7BCC2",
    "lab": {
      "l": 75.83,
      "a": -0.52,
      "b": -3.72
    }
  },
  {
    "name": "14-4509 TPG",
    "rgb": {
      "r": 153,
      "g": 201,
      "b": 223
    },
    "hex": "#99C9DF",
    "lab": {
      "l": 77.74,
      "a": -12.53,
      "b": -17.07
    }
  },
  {
    "name": "14-4605 TPG",
    "rgb": {
      "r": 188,
      "g": 188,
      "b": 185
    },
    "hex": "#BCBCB9",
    "lab": {
      "l": 76,
      "a": -0.01,
      "b": 1.48
    }
  },
  {
    "name": "14-4714 TPG",
    "rgb": {
      "r": 135,
      "g": 213,
      "b": 226
    },
    "hex": "#87D5E2",
    "lab": {
      "l": 80.21,
      "a": -22.78,
      "b": -15.6
    }
  },
  {
    "name": "14-4716 TPG",
    "rgb": {
      "r": 158,
      "g": 211,
      "b": 220
    },
    "hex": "#9ED3DC",
    "lab": {
      "l": 80.78,
      "a": -16.7,
      "b": -11.15
    }
  },
  {
    "name": "14-4912 TPG",
    "rgb": {
      "r": 93,
      "g": 203,
      "b": 200
    },
    "hex": "#5DCBC8",
    "lab": {
      "l": 74.76,
      "a": -33.71,
      "b": -10.16
    }
  },
  {
    "name": "14-5117 TPG",
    "rgb": {
      "r": 112,
      "g": 183,
      "b": 183
    },
    "hex": "#70B7B7",
    "lab": {
      "l": 69.19,
      "a": -23.36,
      "b": -8.77
    }
  },
  {
    "name": "14-5125 TPG",
    "rgb": {
      "r": 72,
      "g": 196,
      "b": 189
    },
    "hex": "#48C4BD",
    "lab": {
      "l": 71.55,
      "a": -37.06,
      "b": -8.82
    }
  },
  {
    "name": "14-5320 TPG",
    "rgb": {
      "r": 106,
      "g": 200,
      "b": 196
    },
    "hex": "#6AC8C4",
    "lab": {
      "l": 74.13,
      "a": -30.1,
      "b": -8.47
    }
  },
  {
    "name": "14-5412 TPG",
    "rgb": {
      "r": 143,
      "g": 203,
      "b": 194
    },
    "hex": "#8FCBC2",
    "lab": {
      "l": 76.84,
      "a": -20.97,
      "b": -3.53
    }
  },
  {
    "name": "14-5419 TPG",
    "rgb": {
      "r": 119,
      "g": 199,
      "b": 186
    },
    "hex": "#77C7BA",
    "lab": {
      "l": 74.18,
      "a": -28.15,
      "b": -3.17
    }
  },
  {
    "name": "14-5520 TPG",
    "rgb": {
      "r": 129,
      "g": 203,
      "b": 198
    },
    "hex": "#81CBC6",
    "lab": {
      "l": 76.35,
      "a": -24.98,
      "b": -6.39
    }
  },
  {
    "name": "14-5612 TPG",
    "rgb": {
      "r": 134,
      "g": 200,
      "b": 188
    },
    "hex": "#86C8BC",
    "lab": {
      "l": 75.45,
      "a": -23.59,
      "b": -2.23
    }
  },
  {
    "name": "14-5618 TPG",
    "rgb": {
      "r": 128,
      "g": 200,
      "b": 185
    },
    "hex": "#80C8B9",
    "lab": {
      "l": 74.96,
      "a": -25.92,
      "b": -1.62
    }
  },
  {
    "name": "14-5710 TPG",
    "rgb": {
      "r": 167,
      "g": 215,
      "b": 194
    },
    "hex": "#A7D7C2",
    "lab": {
      "l": 81.7,
      "a": -19.38,
      "b": 3.74
    }
  },
  {
    "name": "14-5828 TPG",
    "rgb": {
      "r": 108,
      "g": 211,
      "b": 170
    },
    "hex": "#6CD3AA",
    "lab": {
      "l": 76.82,
      "a": -38.82,
      "b": 9.13
    }
  },
  {
    "name": "15-1232 TPG",
    "rgb": {
      "r": 254,
      "g": 168,
      "b": 112
    },
    "hex": "#FEA870",
    "lab": {
      "l": 77.15,
      "a": 29.65,
      "b": 43.28
    }
  },
  {
    "name": "15-1910 TPG",
    "rgb": {
      "r": 244,
      "g": 128,
      "b": 158
    },
    "hex": "#F4809E",
    "lab": {
      "l": 68.31,
      "a": 48.08,
      "b": 7.39
    }
  },
  {
    "name": "15-2122 TPG",
    "rgb": {
      "r": 242,
      "g": 148,
      "b": 173
    },
    "hex": "#F294AD",
    "lab": {
      "l": 72.28,
      "a": 39.26,
      "b": 4.12
    }
  },
  {
    "name": "15-3530 TPG",
    "rgb": {
      "r": 184,
      "g": 163,
      "b": 188
    },
    "hex": "#B8A3BC",
    "lab": {
      "l": 69.41,
      "a": 11.58,
      "b": -9.94
    }
  },
  {
    "name": "15-3615 TPG",
    "rgb": {
      "r": 198,
      "g": 168,
      "b": 209
    },
    "hex": "#C6A8D1",
    "lab": {
      "l": 72.45,
      "a": 16.73,
      "b": -16.14
    }
  },
  {
    "name": "15-3926 TPG",
    "rgb": {
      "r": 145,
      "g": 173,
      "b": 212
    },
    "hex": "#91ADD4",
    "lab": {
      "l": 69.29,
      "a": -3.24,
      "b": -23.35
    }
  },
  {
    "name": "15-3931 TPG",
    "rgb": {
      "r": 143,
      "g": 166,
      "b": 202
    },
    "hex": "#8FA6CA",
    "lab": {
      "l": 66.97,
      "a": -2.2,
      "b": -21.4
    }
  },
  {
    "name": "15-4401 TPG",
    "rgb": {
      "r": 176,
      "g": 169,
      "b": 166
    },
    "hex": "#B0A9A6",
    "lab": {
      "l": 69.68,
      "a": 2.53,
      "b": 2.53
    }
  },
  {
    "name": "15-4512 TPG",
    "rgb": {
      "r": 107,
      "g": 183,
      "b": 194
    },
    "hex": "#6BB7C2",
    "lab": {
      "l": 69.35,
      "a": -22.74,
      "b": -14.5
    }
  },
  {
    "name": "15-4719 TPG",
    "rgb": {
      "r": 97,
      "g": 170,
      "b": 182
    },
    "hex": "#61AAB6",
    "lab": {
      "l": 64.74,
      "a": -21.97,
      "b": -14.4
    }
  },
  {
    "name": "15-4912 TPG",
    "rgb": {
      "r": 101,
      "g": 184,
      "b": 187
    },
    "hex": "#65B8BB",
    "lab": {
      "l": 69.12,
      "a": -26.04,
      "b": -11.23
    }
  },
  {
    "name": "15-5212 TPG",
    "rgb": {
      "r": 155,
      "g": 156,
      "b": 161
    },
    "hex": "#9B9CA1",
    "lab": {
      "l": 64.16,
      "a": 0.95,
      "b": -2.75
    }
  },
  {
    "name": "15-5220 TPG",
    "rgb": {
      "r": 93,
      "g": 183,
      "b": 177
    },
    "hex": "#5DB7B1",
    "lab": {
      "l": 68.17,
      "a": -29.5,
      "b": -7.24
    }
  },
  {
    "name": "15-5810 TPG",
    "rgb": {
      "r": 98,
      "g": 196,
      "b": 157
    },
    "hex": "#62C49D",
    "lab": {
      "l": 71.69,
      "a": -37.78,
      "b": 9
    }
  },
  {
    "name": "16-0005 TPG",
    "rgb": {
      "r": 147,
      "g": 147,
      "b": 152
    },
    "hex": "#939398",
    "lab": {
      "l": 60.8,
      "a": 1.23,
      "b": -3
    }
  },
  {
    "name": "16-1502 TPG",
    "rgb": {
      "r": 141,
      "g": 139,
      "b": 139
    },
    "hex": "#8D8B8B",
    "lab": {
      "l": 57.77,
      "a": 1.57,
      "b": -0.2
    }
  },
  {
    "name": "16-1503 TPG",
    "rgb": {
      "r": 158,
      "g": 156,
      "b": 157
    },
    "hex": "#9E9C9D",
    "lab": {
      "l": 64.39,
      "a": 1.08,
      "b": -0.33
    }
  },
  {
    "name": "16-1523 TPG",
    "rgb": {
      "r": 155,
      "g": 150,
      "b": 151
    },
    "hex": "#9B9697",
    "lab": {
      "l": 62.32,
      "a": 2.74,
      "b": 0.04
    }
  },
  {
    "name": "16-2901 TPG",
    "rgb": {
      "r": 155,
      "g": 152,
      "b": 156
    },
    "hex": "#9B989C",
    "lab": {
      "l": 62.92,
      "a": 2.31,
      "b": -2.03
    }
  },
  {
    "name": "16-3610 TPG",
    "rgb": {
      "r": 169,
      "g": 149,
      "b": 176
    },
    "hex": "#A995B0",
    "lab": {
      "l": 64.19,
      "a": 11.44,
      "b": -10.68
    }
  },
  {
    "name": "16-3615 TPG",
    "rgb": {
      "r": 173,
      "g": 157,
      "b": 184
    },
    "hex": "#AD9DB8",
    "lab": {
      "l": 66.85,
      "a": 9.93,
      "b": -11.27
    }
  },
  {
    "name": "16-3710 TPG",
    "rgb": {
      "r": 162,
      "g": 152,
      "b": 148
    },
    "hex": "#A29894",
    "lab": {
      "l": 63.41,
      "a": 3.44,
      "b": 3.79
    }
  },
  {
    "name": "16-3804 TPG",
    "rgb": {
      "r": 159,
      "g": 155,
      "b": 158
    },
    "hex": "#9F9B9E",
    "lab": {
      "l": 64.25,
      "a": 2.62,
      "b": -1.23
    }
  },
  {
    "name": "16-3928 TPG",
    "rgb": {
      "r": 154,
      "g": 154,
      "b": 183
    },
    "hex": "#9A9AB7",
    "lab": {
      "l": 64.28,
      "a": 4.53,
      "b": -14.96
    }
  },
  {
    "name": "16-4039 TPG",
    "rgb": {
      "r": 120,
      "g": 147,
      "b": 196
    },
    "hex": "#7893C4",
    "lab": {
      "l": 59.85,
      "a": -0.6,
      "b": -29.27
    }
  },
  {
    "name": "16-4705 TPG",
    "rgb": {
      "r": 160,
      "g": 160,
      "b": 161
    },
    "hex": "#A0A0A1",
    "lab": {
      "l": 65.72,
      "a": 0.51,
      "b": -0.46
    }
  },
  {
    "name": "16-4803 TPG",
    "rgb": {
      "r": 136,
      "g": 136,
      "b": 130
    },
    "hex": "#888882",
    "lab": {
      "l": 56.36,
      "a": -1.22,
      "b": 3.52
    }
  },
  {
    "name": "17-0400 TPG",
    "rgb": {
      "r": 135,
      "g": 127,
      "b": 128
    },
    "hex": "#877F80",
    "lab": {
      "l": 53.75,
      "a": 3.59,
      "b": 0.41
    }
  },
  {
    "name": "17-1504 TPG",
    "rgb": {
      "r": 132,
      "g": 131,
      "b": 132
    },
    "hex": "#848384",
    "lab": {
      "l": 54.58,
      "a": 1.37,
      "b": -1.01
    }
  },
  {
    "name": "17-2501 TPG",
    "rgb": {
      "r": 133,
      "g": 125,
      "b": 128
    },
    "hex": "#857D80",
    "lab": {
      "l": 52.84,
      "a": 4.09,
      "b": -0.43
    }
  },
  {
    "name": "17-3927 TPG",
    "rgb": {
      "r": 145,
      "g": 139,
      "b": 145
    },
    "hex": "#918B91",
    "lab": {
      "l": 58.33,
      "a": 3.34,
      "b": -2.16
    }
  },
  {
    "name": "17-4005 TPG",
    "rgb": {
      "r": 132,
      "g": 132,
      "b": 128
    },
    "hex": "#848480",
    "lab": {
      "l": 54.69,
      "a": 0.14,
      "b": 2.16
    }
  },
  {
    "name": "17-4017 TPG",
    "rgb": {
      "r": 128,
      "g": 130,
      "b": 138
    },
    "hex": "#80828A",
    "lab": {
      "l": 54.29,
      "a": 0.71,
      "b": -4.44
    }
  },
  {
    "name": "17-5103 TPG",
    "rgb": {
      "r": 139,
      "g": 138,
      "b": 139
    },
    "hex": "#8B8A8B",
    "lab": {
      "l": 57.56,
      "a": 0.61,
      "b": -0.04
    }
  },
  {
    "name": "17-5800 TPG",
    "rgb": {
      "r": 120,
      "g": 116,
      "b": 113
    },
    "hex": "#787471",
    "lab": {
      "l": 48.87,
      "a": 2.14,
      "b": 1.9
    }
  },
  {
    "name": "18-0205 TPG",
    "rgb": {
      "r": 100,
      "g": 97,
      "b": 93
    },
    "hex": "#64615D",
    "lab": {
      "l": 41.35,
      "a": 0.97,
      "b": 2.99
    }
  },
  {
    "name": "18-0307 TPG",
    "rgb": {
      "r": 105,
      "g": 100,
      "b": 97
    },
    "hex": "#696461",
    "lab": {
      "l": 42.65,
      "a": 1.86,
      "b": 2.53
    }
  },
  {
    "name": "18-0407 TPG",
    "rgb": {
      "r": 111,
      "g": 104,
      "b": 105
    },
    "hex": "#6F6869",
    "lab": {
      "l": 44.48,
      "a": 3.47,
      "b": 0.72
    }
  },
  {
    "name": "18-1408 TPG",
    "rgb": {
      "r": 91,
      "g": 89,
      "b": 85
    },
    "hex": "#5B5955",
    "lab": {
      "l": 37.71,
      "a": 0.69,
      "b": 2.47
    }
  },
  {
    "name": "18-1611 TPG",
    "rgb": {
      "r": 119,
      "g": 114,
      "b": 113
    },
    "hex": "#777271",
    "lab": {
      "l": 48.46,
      "a": 2.25,
      "b": 1.29
    }
  },
  {
    "name": "18-3709 TPG",
    "rgb": {
      "r": 98,
      "g": 90,
      "b": 91
    },
    "hex": "#625A5B",
    "lab": {
      "l": 38.64,
      "a": 4.45,
      "b": 0.18
    }
  },
  {
    "name": "18-3801 TPG",
    "rgb": {
      "r": 121,
      "g": 114,
      "b": 116
    },
    "hex": "#797274",
    "lab": {
      "l": 48.55,
      "a": 3.63,
      "b": -0.13
    }
  },
  {
    "name": "18-3901 TPG",
    "rgb": {
      "r": 87,
      "g": 82,
      "b": 84
    },
    "hex": "#575254",
    "lab": {
      "l": 35.23,
      "a": 2.83,
      "b": -0.43
    }
  },
  {
    "name": "18-3914 TPG",
    "rgb": {
      "r": 92,
      "g": 87,
      "b": 88
    },
    "hex": "#5C5758",
    "lab": {
      "l": 37.2,
      "a": 3.07,
      "b": -0.1
    }
  },
  {
    "name": "18-3924 TPG",
    "rgb": {
      "r": 107,
      "g": 108,
      "b": 120
    },
    "hex": "#6B6C78",
    "lab": {
      "l": 45.61,
      "a": 1.76,
      "b": -6.92
    }
  },
  {
    "name": "18-4007 TPG",
    "rgb": {
      "r": 91,
      "g": 88,
      "b": 92
    },
    "hex": "#5B585C",
    "lab": {
      "l": 37.54,
      "a": 2.26,
      "b": -1.74
    }
  },
  {
    "name": "18-4012 TPG",
    "rgb": {
      "r": 112,
      "g": 109,
      "b": 113
    },
    "hex": "#706D71",
    "lab": {
      "l": 46.03,
      "a": 2.31,
      "b": -1.76
    }
  },
  {
    "name": "18-4021 TPG",
    "rgb": {
      "r": 79,
      "g": 83,
      "b": 92
    },
    "hex": "#4F535C",
    "lab": {
      "l": 34.97,
      "a": 0.31,
      "b": -5.72
    }
  },
  {
    "name": "18-4205 TPG",
    "rgb": {
      "r": 108,
      "g": 117,
      "b": 125
    },
    "hex": "#6C757D",
    "lab": {
      "l": 48.28,
      "a": -1.51,
      "b": -6.13
    }
  },
  {
    "name": "18-4319 TPG",
    "rgb": {
      "r": 103,
      "g": 110,
      "b": 121
    },
    "hex": "#676E79",
    "lab": {
      "l": 45.89,
      "a": -0.62,
      "b": -7.27
    }
  },
  {
    "name": "18-4331 TPG",
    "rgb": {
      "r": 124,
      "g": 123,
      "b": 120
    },
    "hex": "#7C7B78",
    "lab": {
      "l": 51.62,
      "a": 0.01,
      "b": 1.97
    }
  },
  {
    "name": "18-4602 TPG",
    "rgb": {
      "r": 109,
      "g": 111,
      "b": 111
    },
    "hex": "#6D6F6F",
    "lab": {
      "l": 46.54,
      "a": -0.59,
      "b": -0.43
    }
  },
  {
    "name": "18-4705 TPG",
    "rgb": {
      "r": 108,
      "g": 111,
      "b": 115
    },
    "hex": "#6C6F73",
    "lab": {
      "l": 46.6,
      "a": -0.36,
      "b": -2.06
    }
  },
  {
    "name": "18-5103 TPG",
    "rgb": {
      "r": 99,
      "g": 99,
      "b": 98
    },
    "hex": "#636362",
    "lab": {
      "l": 41.65,
      "a": 0.82,
      "b": 0.07
    }
  },
  {
    "name": "19-0503 TPG",
    "rgb": {
      "r": 73,
      "g": 72,
      "b": 72
    },
    "hex": "#494848",
    "lab": {
      "l": 30.7,
      "a": 0.82,
      "b": 0.07
    }
  },
  {
    "name": "19-0505 TPG",
    "rgb": {
      "r": 80,
      "g": 82,
      "b": 78
    },
    "hex": "#50524E",
    "lab": {
      "l": 34.65,
      "a": -1.49,
      "b": 2.49
    }
  },
  {
    "name": "19-0507 TPG",
    "rgb": {
      "r": 79,
      "g": 80,
      "b": 78
    },
    "hex": "#4F504E",
    "lab": {
      "l": 33.87,
      "a": -0.41,
      "b": 1.18
    }
  },
  {
    "name": "19-0610 TPG",
    "rgb": {
      "r": 90,
      "g": 85,
      "b": 84
    },
    "hex": "#5A5554",
    "lab": {
      "l": 36.16,
      "a": 2.73,
      "b": 0.71
    }
  },
  {
    "name": "19-0914 TPG",
    "rgb": {
      "r": 69,
      "g": 63,
      "b": 64
    },
    "hex": "#453F40",
    "lab": {
      "l": 27.25,
      "a": 3.27,
      "b": 0.25
    }
  },
  {
    "name": "19-1011 TPG",
    "rgb": {
      "r": 72,
      "g": 69,
      "b": 74
    },
    "hex": "#48454A",
    "lab": {
      "l": 29.68,
      "a": 2.78,
      "b": -2.64
    }
  },
  {
    "name": "19-3820 TPG",
    "rgb": {
      "r": 64,
      "g": 66,
      "b": 75
    },
    "hex": "#40424B",
    "lab": {
      "l": 27.96,
      "a": 0.54,
      "b": -5.78
    }
  },
  {
    "name": "19-3904 TPG",
    "rgb": {
      "r": 80,
      "g": 77,
      "b": 80
    },
    "hex": "#504D50",
    "lab": {
      "l": 33.12,
      "a": 2,
      "b": -1.14
    }
  },
  {
    "name": "19-3913 TPG",
    "rgb": {
      "r": 75,
      "g": 75,
      "b": 81
    },
    "hex": "#4B4B51",
    "lab": {
      "l": 31.78,
      "a": 1.28,
      "b": -3.28
    }
  },
  {
    "name": "19-3914 TPG",
    "rgb": {
      "r": 90,
      "g": 86,
      "b": 89
    },
    "hex": "#5A5659",
    "lab": {
      "l": 37.01,
      "a": 2.92,
      "b": -1.15
    }
  },
  {
    "name": "19-4000 TPG",
    "rgb": {
      "r": 58,
      "g": 61,
      "b": 64
    },
    "hex": "#3A3D40",
    "lab": {
      "l": 25.55,
      "a": -0.78,
      "b": -2.38
    }
  },
  {
    "name": "19-4001 TPG",
    "rgb": {
      "r": 63,
      "g": 65,
      "b": 64
    },
    "hex": "#3F4140",
    "lab": {
      "l": 27.19,
      "a": -0.54,
      "b": 0.23
    }
  },
  {
    "name": "19-4002 TPG",
    "rgb": {
      "r": 74,
      "g": 72,
      "b": 76
    },
    "hex": "#4A484C",
    "lab": {
      "l": 30.7,
      "a": 1.85,
      "b": -2.09
    }
  },
  {
    "name": "19-4100 TPG",
    "rgb": {
      "r": 68,
      "g": 68,
      "b": 70
    },
    "hex": "#444446",
    "lab": {
      "l": 28.74,
      "a": 0.78,
      "b": -1.37
    }
  },
  {
    "name": "19-4103 TPG",
    "rgb": {
      "r": 58,
      "g": 63,
      "b": 74
    },
    "hex": "#3A3F4A",
    "lab": {
      "l": 26.33,
      "a": 0,
      "b": -7.31
    }
  },
  {
    "name": "19-4204 TPG",
    "rgb": {
      "r": 58,
      "g": 62,
      "b": 66
    },
    "hex": "#3A3E42",
    "lab": {
      "l": 25.62,
      "a": -1.01,
      "b": -3.11
    }
  },
  {
    "name": "19-4206 TPG",
    "rgb": {
      "r": 63,
      "g": 65,
      "b": 68
    },
    "hex": "#3F4144",
    "lab": {
      "l": 27.4,
      "a": 0,
      "b": -2.02
    }
  },
  {
    "name": "19-4209 TPG",
    "rgb": {
      "r": 96,
      "g": 100,
      "b": 107
    },
    "hex": "#60646B",
    "lab": {
      "l": 42,
      "a": -0.16,
      "b": -4.41
    }
  },
  {
    "name": "19-4310 TPG",
    "rgb": {
      "r": 87,
      "g": 92,
      "b": 98
    },
    "hex": "#575C62",
    "lab": {
      "l": 38.47,
      "a": -0.53,
      "b": -4.2
    }
  },
  {
    "name": "19-5303 TPG",
    "rgb": {
      "r": 72,
      "g": 74,
      "b": 76
    },
    "hex": "#484A4C",
    "lab": {
      "l": 30.98,
      "a": -0.46,
      "b": -1.41
    }
  }
]